mypackage/__init__.py
mypackage/_version.py
mypackage/pyadguard.py
pyAdguard-0.2.5.post0.dist-info/LICENSE.txt
pyAdguard-0.2.5.post0.dist-info/METADATA
pyAdguard-0.2.5.post0.dist-info/WHEEL
pyAdguard-0.2.5.post0.dist-info/top_level.txt
pyAdguard-0.2.5.post0.dist-info/RECORD
