Metadata-Version: 2.2
Name: pyAdguard
Version: 0.2.5.post0
Summary: Python Wrapper for the Adguard Home API
Author-email: Lars Jelschen <mail@lars-jelschen.de>
Maintainer-email: Lars Jelschen <mail@lars-jelschen.de>
License: MIT License
Project-URL: homepage, https://github.com/ljelschen/pyadguard
Project-URL: repository, https://github.com/ljelschen/pyadguard
Project-URL: documentation, https://github.com/ljelschen/pyadguard
Keywords: adguard home,adguard,api,wrapper,client
Classifier: Development Status :: 4 - Beta
Classifier: Intended Audience :: Developers
Classifier: Natural Language :: English
Classifier: Programming Language :: Python :: 3.11
Classifier: Programming Language :: Python :: 3.12
Classifier: Programming Language :: Python :: 3
Classifier: Topic :: Software Development :: Libraries :: Python Modules
Requires-Python: >=3.8
License-File: LICENSE.txt
Requires-Dist: python-dotenv
Requires-Dist: requests
